django_telegram/__init__.py
django_telegram/apps.py
django_telegram/bot/__init__.py
django_telegram/bot/bot_runner.py
django_telegram/bot/commands.py
django_telegram/bot/constants.py
django_telegram/bot/decorators/__init__.py
django_telegram/bot/decorators/chat_context.py
django_telegram/bot/decorators/log_args.py
django_telegram/bot/errors/__init__.py
django_telegram/bot/errors/saved_filter_not_found.py
django_telegram/bot/middleware.py
django_telegram/bot/renderers/__init__.py
django_telegram/bot/renderers/qs2md.py
django_telegram/bot/telegram_conversation.py
django_telegram/configurator.py
django_telegram/management/__init__.py
django_telegram/management/commands/__init__.py
django_telegram/management/commands/start_bot.py
telegram_django-1.1.2.dist-info/LICENSE
telegram_django-1.1.2.dist-info/WHEEL
telegram_django-1.1.2.dist-info/METADATA
telegram_django-1.1.2.dist-info/RECORD
