Metadata-Version: 2.1
Name: telegram-django
Version: 1.1.2
Summary: Django Telegram Bot
Home-page: https://connect.cloudblue.com
License: Apache-2.0
Keywords: telegram,connect,utility,cloudblue,bot,django
Author: CloudBlue LLC
Requires-Python: >=3.8,<4.0
Classifier: Development Status :: 5 - Production/Stable
Classifier: Environment :: Console
Classifier: Intended Audience :: Developers
Classifier: License :: OSI Approved :: Apache Software License
Classifier: Operating System :: OS Independent
Classifier: Programming Language :: Python :: 3
Classifier: Programming Language :: Python :: 3.10
Classifier: Programming Language :: Python :: 3.8
Classifier: Programming Language :: Python :: 3.9
Classifier: Topic :: Software Development :: Libraries
Classifier: Topic :: Utilities
Requires-Dist: django (>=2.2,<4)
Requires-Dist: python-telegram-bot (>=13.0.0,<14.0.0)
Project-URL: Repository, https://github.com/cloudblue/telegram-django
